eveo7_mumbleserver_ice/MumbleServer_ice.py
eveo7_mumbleserver_ice/__init__.py
eveo7_mumbleserver_ice-0.0.6.dist-info/METADATA
eveo7_mumbleserver_ice-0.0.6.dist-info/WHEEL
eveo7_mumbleserver_ice-0.0.6.dist-info/RECORD
