Metadata-Version: 2.4
Name: eveo7-mumbleserver-ice
Version: 0.0.6
Summary: Python bindings for interacting with Mumble server using ZeroC's ICE technology.
Project-URL: repository, https://gitlab.com/eveo7/eveo7-mumbleserver-ice
Author-email: Boris Talovikov <boris@talovikov.ru>
Keywords: ice,mumble,murmur,slice2py,zeroc
Requires-Python: <3.13,>=3.12
Requires-Dist: zeroc-ice<3.8,>=3.7.10.1
